demo_uv/__init__.py
demo_uv/cli.py
demo_uv-1.1.10.dist-info/METADATA
demo_uv-1.1.10.dist-info/WHEEL
demo_uv-1.1.10.dist-info/entry_points.txt
demo_uv-1.1.10.dist-info/RECORD
