Metadata-Version: 2.4
Name: demo-uv
Version: 1.1.10
Summary: uv demo
Requires-Python: >=3.10
Requires-Dist: pandas>=2.2.3
Requires-Dist: requests>=2.32.3
